Metadata-Version: 2.1
Name: small-webrtc-prebuilt
Version: 0.3.0
Summary: A simple, ready-to-use client for testing the SmallWebRTCTransport.
License: BSD 2-Clause License
Project-URL: Home, https://github.com/pipecat-ai/small-webrtc-prebuilt
Requires-Dist: fastapi[all]
